nsgcli/__init__.py
nsgcli/agent_commands.py
nsgcli/api.py
nsgcli/device_commands.py
nsgcli/discovery_commands.py
nsgcli/error_handlers.py
nsgcli/exec_commands.py
nsgcli/nsgcli_main.py
nsgcli/nsggnmi_main.py
nsgcli/nsggrok_main.py
nsgcli/nsgql_main.py
nsgcli/response_formatter.py
nsgcli/response_handlers.py
nsgcli/search.py
nsgcli/show.py
nsgcli/silence_main.py
nsgcli/sseclient.py
nsgcli/sub_command.py
nsgcli/system.py
nsgcli/version.py
nsgcli-2.2.8.data/scripts/nsgcli
nsgcli-2.2.8.data/scripts/nsggnmi
nsgcli-2.2.8.data/scripts/nsggrok
nsgcli-2.2.8.data/scripts/nsgql
nsgcli-2.2.8.data/scripts/silence
nsgcli-2.2.8.dist-info/LICENSE
nsgcli-2.2.8.dist-info/METADATA
nsgcli-2.2.8.dist-info/WHEEL
nsgcli-2.2.8.dist-info/top_level.txt
nsgcli-2.2.8.dist-info/RECORD
