Metadata-Version: 2.1
Name: nsgcli
Version: 2.2.8
Summary: NetSpyGlass CLI
Home-page: https://github.com/happygears/nsgcli
Author: Happy Gears, Inc
Author-email: vadim@happygears.net
License: Apache
Keywords: network monitoring NMS netspyglass
Classifier: Development Status :: 4 - Beta
Classifier: License :: OSI Approved :: Apache Software License
Classifier: Programming Language :: Python :: 3.6
Classifier: Programming Language :: Python :: 3.7
Classifier: Programming Language :: Python :: 3.8
Classifier: Programming Language :: Python :: 3.9
Classifier: Topic :: System :: Networking :: Monitoring
Requires-Python: >=3.6
License-File: LICENSE
Requires-Dist: requests
Requires-Dist: requests-unixsocket
Requires-Dist: pyhocon
Requires-Dist: typing
Requires-Dist: python-dateutil
Requires-Dist: pytz
Requires-Dist: tabulate
Requires-Dist: gnmi-proto
Requires-Dist: pandas
Requires-Dist: jsonpath-ng
